STCC/__init__.py
STCC/consensus_STCC.py
tests/__init__.py
STCC-1.0.3.dist-info/LICENSE.txt
STCC-1.0.3.dist-info/METADATA
STCC-1.0.3.dist-info/WHEEL
STCC-1.0.3.dist-info/top_level.txt
STCC-1.0.3.dist-info/RECORD
