Metadata-Version: 2.1
Name: STCC
Version: 1.0.3
Summary: consensus clustering enhances spatial domain detection for spatial transcriptomics data.
Home-page: https://github.com/hucongcong97/STCC
Author: congconghu
Author-email: 2578073006@qq.com
License: MIT
Classifier: Programming Language :: Python
Classifier: Programming Language :: Python :: 3
Classifier: License :: OSI Approved :: MIT License
Classifier: Operating System :: OS Independent
License-File: LICENSE.txt
Requires-Dist: numpy
Requires-Dist: pandas
Requires-Dist: scikit-learn
Requires-Dist: cvxopt
Requires-Dist: scipy
Requires-Dist: seaborn
